trackvia/__init__.py
trackvia-1.0.0.dist-info/DESCRIPTION.rst
trackvia-1.0.0.dist-info/METADATA
trackvia-1.0.0.dist-info/metadata.json
trackvia-1.0.0.dist-info/RECORD
trackvia-1.0.0.dist-info/top_level.txt
trackvia-1.0.0.dist-info/WHEEL
